{
  "chromeWebSecurity": false,
  "projectId": "tidgxq",
  "baseUrl": "http://localhost:8008",
  "reporter": "cypress-multi-reporters",
  "reporterOptions": {
    "reporterEnabled": "mochawesome",
    "mochawesomeReporterOptions": {
      "reportDir": "cypress/reports/mocha",
      "quiet": true,
      "overwrite": false,
      "html": false,
      "json": true
    }
  }
  "env": {
  },
  "integrationFolder": "./cypress/integration",
  "videosFolder": "./cypress/videos",
  "screenshotsFolder": "./cypress/screenshots",
  "supportFile": "./cypress/support/index.js",
  "pluginsFile": "./cypress/plugins/index.js"
}
